.travis.yml
Pipfile
Pipfile.lock
README.md
__init__.py
codecov.yml
setup.py
smach/__init__.py
smach/concurrence.py
smach/container.py
smach/exceptions.py
smach/iterator.py
smach/log.py
smach/sequence.py
smach/state.py
smach/state_machine.py
smach/user_data.py
smach/util.py
standalone_smach.egg-info/PKG-INFO
standalone_smach.egg-info/SOURCES.txt
standalone_smach.egg-info/dependency_links.txt
standalone_smach.egg-info/top_level.txt
tests/__init__.py
tests/conftest.py
tests/test_simple.py