Metadata-Version: 2.1
Name: standalone-smach
Version: 0.0.8
Summary: Standalone fork of ros smach
Home-page: https://github.com/gabrielsr/standalone-smach
Author: Gabriel Rodrigues
Author-email: gabrielsr@gmail.com
License: UNKNOWN
Platform: UNKNOWN
Classifier: Programming Language :: Python :: 3
Classifier: License :: OSI Approved :: MIT License
Classifier: Operating System :: OS Independent
Requires-Python: >=3.8
